tf_encrypt/__init__.py
tf_encrypt/tf_encrypt.py
tf_encrypt/tf_encrypt_fernet.py
tf_encrypts-1.0.5.dist-info/METADATA
tf_encrypts-1.0.5.dist-info/WHEEL
tf_encrypts-1.0.5.dist-info/top_level.txt
tf_encrypts-1.0.5.dist-info/RECORD
