Metadata-Version: 2.1
Name: tf-encrypts
Version: 1.0.5
Summary: TfEncrypt
Home-page: UNKNOWN
Author: kkh
Author-email: doggood720@gmail.com
License: MIT
Platform: UNKNOWN
Requires-Dist: Fernet
Requires-Dist: pycryptodome
